LICENSE.txt
README.md
setup.py
src/gkamin_calculator/__init__.py
src/gkamin_calculator/gkamin_calculator.py
src/gkamin_calculator.egg-info/PKG-INFO
src/gkamin_calculator.egg-info/SOURCES.txt
src/gkamin_calculator.egg-info/dependency_links.txt
src/gkamin_calculator.egg-info/requires.txt
src/gkamin_calculator.egg-info/top_level.txt